gif_to_video/__init__.py
gif_to_video/gif_to_video.py
gif_to_video/test/__init__.py
gif_to_video/test/test_gif_to_video.py
GifToVideo-0.1.0.dist-info/LICENSE
GifToVideo-0.1.0.dist-info/METADATA
GifToVideo-0.1.0.dist-info/WHEEL
GifToVideo-0.1.0.dist-info/entry_points.txt
GifToVideo-0.1.0.dist-info/top_level.txt
GifToVideo-0.1.0.dist-info/RECORD
