Metadata-Version: 2.1
Name: GifToVideo
Version: 0.1.0
Summary: An application that converts animated .GIF files into videos.
Home-page: https://github.com/Drakovek/GifToVideo
Author: Drakovek
Author-email: DrakovekMail@gmail.com
Classifier: Programming Language :: Python :: 3
Classifier: License :: OSI Approved :: GNU General Public License v3 (GPLv3)
Classifier: Operating System :: OS Independent
Requires-Python: >=3.0
License-File: LICENSE
Requires-Dist: python-ffmpeg
Requires-Dist: pillow
